[{
        "id": 1,
        "questions": "Nested Lops And Coding Questions",
        "roughSolution": true,
        "testCases": true,
        "prefilledCode": true,
        "solutionApproach": false,
        "cleanSolution": false
    },
    {
        "id": 2,
        "questions": "observable Loops And Coing Questions",
        "roughSolution": false,
        "testCases": true,
        "prefilledCode": false,
        "solutionApproach": true,
        "cleanSolution": false
    },
    {
        "id": 3,
        "questions": "Anbb Lops And Coding Questions",
        "roughSolution": false,
        "testCases": false,
        "prefilledCode": true,
        "solutionApproach": true,
        "cleanSolution": false
    },
    {
        "id": 4,
        "questions": "constants ested Loops Ad Coding Questions",
        "roughSolution": true,
        "testCases": false,
        "prefilledCode": false,
        "solutionApproach": true,
        "cleanSolution": false
    },
    {
        "id": 5,
        "questions": "kjkhg Loops And Coding Questions",
        "roughSolution": true,
        "testCases": false,
        "prefilledCode": true,
        "solutionApproach": true,
        "cleanSolution": true
    },
    {
        "id": 6,
        "questions": "saveUserSolution Loops And Coding Questions",
        "roughSolution": true,
        "testCases": true,
        "prefilledCode": true,
        "solutionApproach": false,
        "cleanSolution": false
    },
    {
        "id": 7,
        "questions": "jatf Loops And Codng Questions",
        "roughSolution": true,
        "testCases": false,
        "prefilledCode": true,
        "solutionApproach": true,
        "cleanSolution": false
    },
    {
        "id": 7,
        "questions": "log Loops nd Coding Questions",
        "roughSolution": true,
        "testCases": false,
        "prefilledCode": true,
        "solutionApproach": true,
        "cleanSolution": false
    },
    {
        "id": 8,
        "questions": "Hi Lops And Coding Questions",
        "roughSolution": true,
        "testCases": false,
        "prefilledCode": true,
        "solutionApproach": true,
        "cleanSolution": false
    },
    {
        "id": 9,
        "questions": "userData Loops And Coding Questons",
        "roughSolution": true,
        "testCases": false,
        "prefilledCode": true,
        "solutionApproach": true,
        "cleanSolution": false
    },
    {
        "id": 10,
        "questions": "Map Loops And Codin Questions",
        "roughSolution": true,
        "testCases": false,
        "prefilledCode": true,
        "solutionApproach": true,
        "cleanSolution": false
    }

]
